examples/classifiers/binary.py
examples/text_classification.py
farglot/__farcaster/__init__.py
farglot/__farcaster/builders.py
farglot/__farcaster/client.py
farglot/__farcaster/generated/gossip_pb2.py
farglot/__farcaster/generated/gossip_pb2.pyi
farglot/__farcaster/generated/gossip_pb2_grpc.py
farglot/__farcaster/generated/hub_event_pb2.py
farglot/__farcaster/generated/hub_event_pb2.pyi
farglot/__farcaster/generated/hub_event_pb2_grpc.py
farglot/__farcaster/generated/hub_state_pb2.py
farglot/__farcaster/generated/hub_state_pb2.pyi
farglot/__farcaster/generated/hub_state_pb2_grpc.py
farglot/__farcaster/generated/id_registry_event_pb2.py
farglot/__farcaster/generated/id_registry_event_pb2.pyi
farglot/__farcaster/generated/id_registry_event_pb2_grpc.py
farglot/__farcaster/generated/job_pb2.py
farglot/__farcaster/generated/job_pb2.pyi
farglot/__farcaster/generated/job_pb2_grpc.py
farglot/__farcaster/generated/message_pb2.py
farglot/__farcaster/generated/message_pb2.pyi
farglot/__farcaster/generated/message_pb2_grpc.py
farglot/__farcaster/generated/name_registry_event_pb2.py
farglot/__farcaster/generated/name_registry_event_pb2.pyi
farglot/__farcaster/generated/name_registry_event_pb2_grpc.py
farglot/__farcaster/generated/onchain_event_pb2.py
farglot/__farcaster/generated/onchain_event_pb2.pyi
farglot/__farcaster/generated/onchain_event_pb2_grpc.py
farglot/__farcaster/generated/request_response_pb2.py
farglot/__farcaster/generated/request_response_pb2.pyi
farglot/__farcaster/generated/request_response_pb2_grpc.py
farglot/__farcaster/generated/rpc_pb2.py
farglot/__farcaster/generated/rpc_pb2.pyi
farglot/__farcaster/generated/rpc_pb2_grpc.py
farglot/__farcaster/generated/sync_trie_pb2.py
farglot/__farcaster/generated/sync_trie_pb2.pyi
farglot/__farcaster/generated/sync_trie_pb2_grpc.py
farglot/__farcaster/generated/username_proof_pb2.py
farglot/__farcaster/generated/username_proof_pb2.pyi
farglot/__farcaster/generated/username_proof_pb2_grpc.py
farglot-0.1.3.dist-info/entry_points.txt
farglot-0.1.3.dist-info/LICENSE
farglot-0.1.3.dist-info/WHEEL
farglot-0.1.3.dist-info/METADATA
farglot-0.1.3.dist-info/RECORD
