Metadata-Version: 2.1
Name: farglot
Version: 0.1.3
Summary: A Transformer-based SocialNLP toolkit for Farcaster
Home-page: https://github.com/michaelhly/FarGlot
License: MIT
Author: michaelhly
Author-email: michaelhly@gmail.com
Requires-Python: >=3.9,<3.11
Classifier: License :: OSI Approved :: MIT License
Classifier: Programming Language :: Python :: 3
Classifier: Programming Language :: Python :: 3.10
Classifier: Programming Language :: Python :: 3.9
Provides-Extra: cli
Requires-Dist: PyNaCl (>=1.5.0,<2.0.0); extra == "cli"
Requires-Dist: blake3 (>=0.3.3,<0.4.0); extra == "cli"
Requires-Dist: datasets (>=2.14.3,<3.0.0)
Requires-Dist: eth-account (>=0.9.0,<0.10.0)
Requires-Dist: faust-streaming-rocksdb (>=0.9.2,<0.10.0); extra == "cli"
Requires-Dist: grpcio (==1.53.0); extra == "cli"
Requires-Dist: protobuf (==4.22.1); extra == "cli"
Requires-Dist: torch (>=2.0.1,<3.0.0)
Requires-Dist: transformers (>=4.31.0,<5.0.0)
Requires-Dist: typer[all] (>=0.9.0,<0.10.0); extra == "cli"
Project-URL: Repository, https://github.com/michaelhly/FarGlot
